fastdbt/__init__.py
fastdbt-0.1.1.dist-info/WHEEL
fastdbt-0.1.1.dist-info/entry_points.txt
fastdbt-0.1.1.dist-info/METADATA
fastdbt-0.1.1.dist-info/RECORD
