Metadata-Version: 2.3
Name: fastdbt
Version: 0.1.1
Summary: fastdbt
Author: Cody
Author-email: Cody <cody@dkdc.dev>
Requires-Python: >=3.13
